setup.py
transmute/__init__.py
transmute/_version.py
transmute/basket.py
transmute/bootstrap.py
transmute/resolver.py
transmute/s3.py
transmute/transmuter.py
transmute.egg-info/PKG-INFO
transmute.egg-info/SOURCES.txt
transmute.egg-info/dependency_links.txt
transmute.egg-info/top_level.txt