Metadata-Version: 1.0
Name: transmute
Version: 5.0
Summary: Automatically update Python Eggs on application startup.
Home-page: https://github.com/comoyo/python-transmute
Author: João Abecasis
Author-email: joao@comoyo.com
License: UNKNOWN
Platform: UNKNOWN
Classifier: Programming Language :: Python
Classifier: License :: OSI Approved :: Apache Software License
Classifier: Operating System :: OS Independent
Classifier: Development Status :: 3 - Alpha
Classifier: Intended Audience :: Developers
Classifier: Topic :: Software Development :: Libraries :: Python Modules
Classifier: Topic :: System :: Installation/Setup
Classifier: Topic :: System :: Software Distribution
